{
    "#comment": "Pet UI",
    "add": {
    },
    "edit": [
        {
            "#comment": "Ally's Heart",
            "mid": "130391",
            "match": "",
            "value": "Current Pet %s is Level %d. When exchanged, you will get x%d %s."
        },
        {
            "#comment": "Pet speech limit",
            "mid": "130236",
            "match": "Can input up to 30 letters.",
            "value": "Maximum 30 chars"
        }
    ],
    "#old": [
        {
            "#comment": "Pet speech shortcut",
            "mid": "130237",
            "match": "130237",
            "value": "Tip: Use the '/pet <msg>' chat command to quickly update your ally speech bubble"
        },
        {
            "#comment": "Pet speech clear shortcut",
            "mid": "130245",
            "match": "130245",
            "value": "Tip: Use the '/petoff' chat command to turn off your ally speech bubble"
        }
    ]
}
